traceai_haystack/__init__.py
traceai_haystack/_wrappers.py
traceai_haystack/version.py
traceai_haystack-0.1.8.dist-info/METADATA
traceai_haystack-0.1.8.dist-info/WHEEL
traceai_haystack-0.1.8.dist-info/RECORD
